uwastro465isos/__init__.py
uwastro465isos/isochrones.py
uwastro465isos/data/__init__.py
uwastro465isos/data/isochrones_ubvrijhk.dat
uwastro465isos/data/isochrones_ugriz.dat
uwastro465isos-0.1.0.dist-info/METADATA
uwastro465isos-0.1.0.dist-info/WHEEL
uwastro465isos-0.1.0.dist-info/top_level.txt
uwastro465isos-0.1.0.dist-info/RECORD
